LICENSE
MANIFEST.in
README.md
README.rst
setup.py
sparsity_pattern/__init__.py
sparsity_pattern/experimental.py
sparsity_pattern/generators.py
sparsity_pattern/utils.py
sparsity_pattern.egg-info/PKG-INFO
sparsity_pattern.egg-info/SOURCES.txt
sparsity_pattern.egg-info/dependency_links.txt
sparsity_pattern.egg-info/top_level.txt
sparsity_pattern.egg-info/zip-safe
test/__init__.py
test/test_sparsity_pattern.py