Metadata-Version: 2.1
Name: sparsity-pattern
Version: 0.4.3
Summary: Generate different types of sparsity pattern for sparse matrices.
Home-page: http://github.com/ulf1/sparsity-pattern
Author: Ulf Hamster
Author-email: 554c46@gmail.com
License: Apache License 2.0
Requires-Python: >=3.6
License-File: LICENSE
